{
  "kind": "collectionType",
  "collectionName": "kerjasamas",
  "info": {
    "name": "Kerjasama",
    "description": ""
  },
  "options": {
    "increments": true,
    "timestamps": true,
    "draftAndPublish": true
  },
  "pluginOptions": {},
  "attributes": {
    "mitra": {
      "type": "string",
      "required": true
    },
    "deskripsi": {
      "type": "richtext",
      "required": true
    },
    "attachment": {
      "collection": "file",
      "via": "related",
      "allowedTypes": [
        "files",
        "images",
        "videos"
      ],
      "plugin": "upload",
      "required": true,
      "pluginOptions": {}
    }
  }
}
